<?xml version="1.0" encoding="UTF-8" standalone="yes"?>
<cp:coreProperties xmlns:cp="http://schemas.openxmlformats.org/package/2006/metadata/core-properties" xmlns:dc="http://purl.org/dc/elements/1.1/" xmlns:dcterms="http://purl.org/dc/terms/" xmlns:dcmitype="http://purl.org/dc/dcmitype/" xmlns:xsi="http://www.w3.org/2001/XMLSchema-instance"><dc:title>HTML-and-CSS-Exam</dc:title><dc:subject>Software Development</dc:subject><dc:creator>Software University</dc:creator><cp:keywords>SoftUni; Software University; programming; coding; computer programming; software development; software engineering; software technologies; digital skills; technical skills; training; course</cp:keywords><dc:description>© SoftUni – https://softuni.org_x000d_
© Software University – https://softuni.bg_x000d_
_x000d_
Copyrighted document. Unauthorized copy, reproduction or use is not permitted.</dc:description><cp:lastModifiedBy>Boryana Dimitrova</cp:lastModifiedBy><cp:revision>350</cp:revision><cp:lastPrinted>2015-10-26T22:35:00Z</cp:lastPrinted><dcterms:created xsi:type="dcterms:W3CDTF">2019-11-12T12:29:00Z</dcterms:created><dcterms:modified xsi:type="dcterms:W3CDTF">2023-05-23T13:01:00Z</dcterms:modified><cp:category>computer programming;programming;software development;software engineering</cp:category></cp:coreProperties>